skynamo/__init__.py
skynamo/integration_helpers/__init__.py
skynamo/integration_helpers/syncTaxRatesAndWarehouses.py
skynamo/main/CreditRequest.py
skynamo/main/CustomForm.py
skynamo/main/Customer.py
skynamo/main/Order.py
skynamo/main/Product.py
skynamo/main/Quote.py
skynamo/main/Reader.py
skynamo/main/Writer.py
skynamo/main/__init__.py
skynamo/models/Address.py
skynamo/models/CustomFieldsToCreate.py
skynamo/models/CustomFormBase.py
skynamo/models/Invoice.py
skynamo/models/InvoiceItem.py
skynamo/models/LineItem.py
skynamo/models/Location.py
skynamo/models/OrderUnit.py
skynamo/models/Price.py
skynamo/models/PriceList.py
skynamo/models/StockLevel.py
skynamo/models/TaxRate.py
skynamo/models/Transaction.py
skynamo/models/User.py
skynamo/models/VisitFrequency.py
skynamo/models/Warehouse.py
skynamo/models/__init__.py
skynamo/outputters/__init__.py
skynamo/outputters/csvWriter.py
skynamo/outputters/emailer.py
skynamo/reader/ReaderBase.py
skynamo/reader/__init__.py
skynamo/reader/jsonToObjects.py
skynamo/reader/readerHelpers.py
skynamo/reader/sync.py
skynamo/refresher/CustomFieldArg.py
skynamo/refresher/InstanceClassContentsCls.py
skynamo/refresher/__init__.py
skynamo/refresher/refreshHelpers.py
skynamo/shared/__init__.py
skynamo/shared/api.py
skynamo/shared/helpers.py
skynamo/writer/WriteErrorCls.py
skynamo/writer/WriteOperationCls.py
skynamo/writer/WriterBase.py
skynamo/writer/__init__.py
skynamo/writer/execute.py
skynamo/writer/writeHelpers.py
skynamo-0.0.25.dist-info/LICENSE.txt
skynamo-0.0.25.dist-info/METADATA
skynamo-0.0.25.dist-info/WHEEL
skynamo-0.0.25.dist-info/top_level.txt
skynamo-0.0.25.dist-info/RECORD
