Metadata-Version: 2.1
Name: skynamo
Version: 0.0.25
Summary: Skynamo Public API SDK
Home-page: https://github.com/skynamo/skynamo-python-sdk
Author: Daniel van Niekerk
Author-email: daniel@skynamo.com
License-File: LICENSE.txt
Requires-Dist: requests
